lputils/__init__.py
lputils/defaults.py
lputils/sizes.py
latex_plot_utils-2.0.0.dist-info/LICENSE
latex_plot_utils-2.0.0.dist-info/METADATA
latex_plot_utils-2.0.0.dist-info/WHEEL
latex_plot_utils-2.0.0.dist-info/top_level.txt
latex_plot_utils-2.0.0.dist-info/RECORD
