Metadata-Version: 2.1
Name: latex-plot-utils
Version: 2.0.0
Summary: Helpers for Matplotlib plots in LaTeX
Home-page: https://github.com/Baltoli/latex-plot-utils
Author: Bruce Collie
Author-email: brucecollie82@gmail.com
License: UNKNOWN
Platform: UNKNOWN
Classifier: Programming Language :: Python :: 3
Classifier: License :: OSI Approved :: MIT License
Classifier: Operating System :: OS Independent
Requires-Python: >=3.6
Requires-Dist: matplotlib
